README.md
setup.cfg
setup.py
tapsaff/__init__.py
tapsaff.egg-info/PKG-INFO
tapsaff.egg-info/SOURCES.txt
tapsaff.egg-info/dependency_links.txt
tapsaff.egg-info/requires.txt
tapsaff.egg-info/top_level.txt