Metadata-Version: 1.1
Name: tapsaff
Version: 0.2.0
Summary: Provides an API for requesting information from taps-aff.co.uk
Home-page: https://github.com/bazwilliams/python-taps-aff
Author: Barry John Williams
Author-email: barry@bjw.me.uk
License: UNKNOWN
Download-URL: https://github.com/bazwilliams/python-taps-aff/tarball/0.2.0
Keywords: weather,glasgow,uk,clothes,top,taps,aff,oan
Platform: UNKNOWN
